vstatistic/__init__.py
vstatistic/core.py
vstatistic/metrics.py
vstatistic/plot.py
vstatistic/plotting/__init__.py
vstatistic/plotting/core.py
vstatistic/plotting/wrappers.py
vstatistic/report.html
vstatistic/utils.py
vstatistic-1.1.10.dist-info/LICENSE
vstatistic-1.1.10.dist-info/METADATA
vstatistic-1.1.10.dist-info/WHEEL
vstatistic-1.1.10.dist-info/RECORD
