Metadata-Version: 2.1
Name: vstatistic
Version: 1.1.10
Summary: vStatistic: A Portfolio analytics for quants
Home-page: https://quant.vn
License: MIT
Author: thync
Author-email: thync@outlook.com
Requires-Python: >=3.9,<4.0
Classifier: Intended Audience :: Developers
Classifier: License :: OSI Approved :: MIT License
Classifier: Operating System :: MacOS
Classifier: Operating System :: Microsoft :: Windows
Classifier: Operating System :: OS Independent
Classifier: Operating System :: POSIX
Classifier: Operating System :: POSIX :: Linux
Classifier: Programming Language :: Python :: 3
Classifier: Programming Language :: Python :: 3.9
Classifier: Programming Language :: Python :: 3.10
Classifier: Programming Language :: Python :: 3.11
Classifier: Programming Language :: Python :: 3.12
Classifier: Topic :: Software Development :: Libraries :: Python Modules
Classifier: Typing :: Typed
Requires-Dist: matplotlib (>=3.9.2,<4.0.0)
Requires-Dist: packaging (>=24.1,<25.0)
Requires-Dist: pandas (>=2.2.2,<3.0.0)
Requires-Dist: plotly (>=5.24.0,<6.0.0)
Requires-Dist: scipy (>=1.2,<2.0)
Requires-Dist: seaborn (>=0.13.2,<0.14.0)
Requires-Dist: tabulate (>=0.9.0,<0.10.0)
Project-URL: Repository, https://github.com/quant-vn/vstatistic
